jalali_date/__init__.py
jalali_date/admin.py
jalali_date/fields.py
jalali_date/settings.py
jalali_date/widgets.py
jalali_date/static/admin/jquery.ui.datepicker.jalali/default.htm
jalali_date/static/admin/jquery.ui.datepicker.jalali/scripts/calendar.all.js
jalali_date/static/admin/jquery.ui.datepicker.jalali/scripts/calendar.js
jalali_date/static/admin/jquery.ui.datepicker.jalali/scripts/jquery-1.10.2.min.js
jalali_date/static/admin/jquery.ui.datepicker.jalali/scripts/jquery-1.10.2.min.map
jalali_date/static/admin/jquery.ui.datepicker.jalali/scripts/jquery.ui.core.js
jalali_date/static/admin/jquery.ui.datepicker.jalali/scripts/jquery.ui.datepicker-cc-fa.js
jalali_date/static/admin/jquery.ui.datepicker.jalali/scripts/jquery.ui.datepicker-cc.js
jalali_date/static/admin/jquery.ui.datepicker.jalali/themes/base/jquery-ui.min.css
jalali_date/static/admin/jquery.ui.datepicker.jalali/themes/base/images/ui-icons_444444_256x240.png
jalali_date/static/admin/jquery.ui.datepicker.jalali/themes/base/images/ui-icons_555555_256x240.png
jalali_date/static/admin/jquery.ui.datepicker.jalali/themes/base/images/ui-icons_777620_256x240.png
jalali_date/static/admin/jquery.ui.datepicker.jalali/themes/base/images/ui-icons_777777_256x240.png
jalali_date/static/admin/jquery.ui.datepicker.jalali/themes/base/images/ui-icons_cc0000_256x240.png
jalali_date/static/admin/jquery.ui.datepicker.jalali/themes/base/images/ui-icons_ffffff_256x240.png
jalali_date/static/admin/js/django_jalali..js
jalali_date/static/admin/js/django_jalali.min.js
jalali_date/static/admin/js/main.js
jalali_date/templates/admin/jalali_change_form.html
jalali_date/templates/admin/edit_inline/jalali_stacked.html
jalali_date/templates/admin/edit_inline/jalali_tabular.html
jalali_date/templates/admin/includes/jalali_fieldset.html
jalali_date/templates/admin/widgets/jalali_split_datetime.html
jalali_date/templatetags/__init__.py
jalali_date/templatetags/jalali_tags.py
tests/__init__.py
tests/test_settings.py
django_jalali_date-1.1.2.dist-info/LICENSE
django_jalali_date-1.1.2.dist-info/METADATA
django_jalali_date-1.1.2.dist-info/WHEEL
django_jalali_date-1.1.2.dist-info/top_level.txt
django_jalali_date-1.1.2.dist-info/RECORD
