Metadata-Version: 2.1
Name: django-jalali-date
Version: 1.1.2
Summary: Jalali Date support for user interface. Easy conversion of DateTimeFiled to JalaliDateTimeField within the admin site, views, forms and templates.
Home-page: http://github.com/a-roomana/django-jalali-date
Download-URL: https://pypi.python.org/pypi/django-jalali-date/
Author: Arman Roomana
Author-email: roomana.arman@gmail.com
License: MIT
Keywords: django jalali date
Platform: any
Classifier: Environment :: Web Environment
Classifier: Intended Audience :: Developers
Classifier: Operating System :: OS Independent
Classifier: Topic :: Software Development :: Libraries :: Application Frameworks
Classifier: Topic :: Software Development :: Libraries :: Python Modules
Classifier: Programming Language :: Python
Classifier: Programming Language :: Python :: 3.8
Classifier: Programming Language :: Python :: 3.9
Classifier: Programming Language :: Python :: 3.10
Classifier: Programming Language :: Python :: 3.11
Classifier: Framework :: Django
Classifier: Framework :: Django :: 2.2
Classifier: Framework :: Django :: 3.2
Classifier: Framework :: Django :: 4.2
Classifier: Framework :: Django :: 5.0
Requires-Python: >=3
License-File: LICENSE
Requires-Dist: django
Requires-Dist: jdatetime
